{
"type": "FeatureCollection",
"name": "prison",
"crs": { "type": "name", "properties": { "name": "urn:ogc:def:crs:OGC:1.3:CRS84" } },
"features": [
{ "type": "Feature", "properties": { "amenity": "prison", "name": "Исправительная колония № 2", "capacity": 4000 }, "geometry": { "type": "Point", "coordinates": [ 60.580396116580744, 56.82940565 ] } },
{ "type": "Feature", "properties": { "amenity": "prison", "name": "Следственный изолятор №1", "capacity": 4000 }, "geometry": { "type": "Point", "coordinates": [ 60.578055620589765, 56.83061495 ] } },
{ "type": "Feature", "properties": { "amenity": "prison", "name": "Исправительная колония №10", "capacity": 4000 }, "geometry": { "type": "Point", "coordinates": [ 60.620258158669259, 56.78235695 ] } },
{ "type": "Feature", "properties": { "amenity": "prison", "name": "Следственный изолятор №5", "capacity": 4000 }, "geometry": { "type": "Point", "coordinates": [ 60.626513216111455, 56.7644816 ] } }
]
}
